MANIFEST.in
setup.py
./__init__.py
./__openerp__.py
doc/TODO.txt
i18n/ar.po
i18n/bg.po
i18n/bn.po
i18n/bs.po
i18n/ca.po
i18n/cs.po
i18n/da.po
i18n/de.po
i18n/en_AU.po
i18n/en_GB.po
i18n/es.po
i18n/es_CL.po
i18n/es_CR.po
i18n/es_DO.po
i18n/es_EC.po
i18n/es_MX.po
i18n/et.po
i18n/fa.po
i18n/fi.po
i18n/fr.po
i18n/fr_CA.po
i18n/gl.po
i18n/gu.po
i18n/he.po
i18n/hr.po
i18n/hu.po
i18n/it.po
i18n/ja.po
i18n/ka.po
i18n/ko.po
i18n/lt.po
i18n/mk.po
i18n/mn.po
i18n/nb.po
i18n/nl.po
i18n/nl_BE.po
i18n/pl.po
i18n/pt.po
i18n/pt_BR.po
i18n/ro.po
i18n/ru.po
i18n/sl.po
i18n/sq.po
i18n/sr@latin.po
i18n/sv.po
i18n/th.po
i18n/tr.po
i18n/web_graph.pot
i18n/zh_CN.po
openerp_web_graph.egg-info/PKG-INFO
openerp_web_graph.egg-info/SOURCES.txt
openerp_web_graph.egg-info/dependency_links.txt
openerp_web_graph.egg-info/requires.txt
openerp_web_graph.egg-info/top_level.txt
static/lib/dropdown.js
static/lib/flotr2/flotr2.examples.min.js
static/lib/flotr2/flotr2.examples.types.js
static/lib/flotr2/flotr2.ie.min.js
static/lib/flotr2/flotr2.js
static/lib/flotr2/flotr2.min.js
static/lib/flotr2/js/Axis.js
static/lib/flotr2/js/Color.js
static/lib/flotr2/js/DOM.js
static/lib/flotr2/js/Date.js
static/lib/flotr2/js/DefaultOptions.js
static/lib/flotr2/js/EventAdapter.js
static/lib/flotr2/js/Flotr.js
static/lib/flotr2/js/Graph.js
static/lib/flotr2/js/Series.js
static/lib/flotr2/js/Text.js
static/lib/flotr2/js/plugins/crosshair.js
static/lib/flotr2/js/plugins/download.js
static/lib/flotr2/js/plugins/grid.js
static/lib/flotr2/js/plugins/handles.js
static/lib/flotr2/js/plugins/hit.js
static/lib/flotr2/js/plugins/labels.js
static/lib/flotr2/js/plugins/legend.js
static/lib/flotr2/js/plugins/selection.js
static/lib/flotr2/js/plugins/spreadsheet.js
static/lib/flotr2/js/plugins/titles.js
static/lib/flotr2/js/types/bars.js
static/lib/flotr2/js/types/bubbles.js
static/lib/flotr2/js/types/candles.js
static/lib/flotr2/js/types/gantt.js
static/lib/flotr2/js/types/lines.js
static/lib/flotr2/js/types/markers.js
static/lib/flotr2/js/types/pie.js
static/lib/flotr2/js/types/points.js
static/lib/flotr2/js/types/radar.js
static/lib/flotr2/js/types/timeline.js
static/lib/flotr2/lib/base64.js
static/lib/flotr2/lib/bean-min.js
